INSTALL
MANIFEST.in
README
TODO
setup.py
ISO8583/ISO8583.py
ISO8583/ISOErrors.py
ISO8583/__init__.py
ISO8583.egg-info/PKG-INFO
ISO8583.egg-info/SOURCES.txt
ISO8583.egg-info/dependency_links.txt
ISO8583.egg-info/top_level.txt
doc/ISO8583.ISO8583.html
doc/ISO8583.ISOErrors.html
doc/ISO8583.html
examples/echoClient.py
examples/echoServer.py
examples/example1.py
examples/example2.py
examples/example3.py
examples/example4.py