Metadata-Version: 1.0
Name: ISO8583
Version: 1.3.5
Summary: ISO8583 LIBRARY
Home-page: https://github.com/ducminhgd/python-ISOMessage8583
Author: Gia Duong Duc Minh
Author-email: giaduongducminh@gmail.com
License: UNKNOWN
Keywords: ISO8583
Platform: UNKNOWN
